<?xml version="1.0"?>
<unit xmlns="http://qcad.org/namespaces/src" xmlns:qc="http://qcad.org/namespaces/xsl" filename="RFontChooserWidget.h">
  <class_decl name="QLabel" />
  <class name="RFontChooserWidget">
    <super_list>
      <super name="QObject" />
      <super name="QWidget" />
    </super_list>
    <property type="QFont" name="chosenFont" read="getChosenFont" write="setChosenFont" />
    <constructor>
      <variant>
        <parameters>
          <parameter const="false" type="QWidget" modifier="*" name="parent" default="0" />
        </parameters>
      </variant>
    </constructor>
    <function name="getChosenFont">
      <variant return-type="QFont" const="true" access="public">
        <parameters />
      </variant>
    </function>
    <function name="setChosenFont">
      <variant return-type="void" access="public">
        <parameters>
          <parameter const="true" type="QFont" modifier="&amp;" name="font" />
        </parameters>
      </variant>
    </function>
    <function name="getSize">
      <variant return-type="int" const="true" access="public">
        <parameters />
      </variant>
    </function>
    <function name="setSize">
      <variant return-type="void" access="public">
        <parameters>
          <parameter const="false" type="int" modifier="" name="size" />
        </parameters>
      </variant>
    </function>
    <function name="getLabel">
      <variant return-type="QString" const="true" access="public">
        <parameters />
      </variant>
    </function>
    <function name="setLabel">
      <variant return-type="void" access="public">
        <parameters>
          <parameter const="true" type="QString" modifier="&amp;" name="l" />
        </parameters>
      </variant>
    </function>
    <function name="valueChanged">
      <variant return-type="void" access="public" signal="true">
        <parameters>
          <parameter const="true" type="QFont" modifier="&amp;" name="font" />
        </parameters>
      </variant>
    </function>
    <function name="chosenFontChanged">
      <variant return-type="void" access="public">
        <parameters>
          <parameter const="true" type="QFont" modifier="&amp;" name="font" />
        </parameters>
      </variant>
    </function>
    <function name="sizeChanged">
      <variant return-type="void" access="public">
        <parameters>
          <parameter const="false" type="int" modifier="" name="index" />
        </parameters>
      </variant>
    </function>
    <function name="resizeEvent">
      <variant return-type="void" access="protected">
        <parameters>
          <parameter const="false" type="QResizeEvent" modifier="*" name="event" />
        </parameters>
      </variant>
    </function>
    <function name="updateSizeCombo" />
  </class>
</unit>
